[
  {
    "TimeStamp": "8/29/2022 15:11:21",
    "Name": "Clinton Otse",
    "Email": "clicksketch60@gmail.com",
    "InitialApplications": "No",
    "CV": "https://drive.google.com/open?id=1nBfVClV_Y2boX0MkvPZ4ZLRKXeoCZtJB"
  },
  {
    "TimeStamp": "8/29/2022 16:32:12",
    "Name": "Moses",
    "Email": "abubakarmoses@yahoo.com",
    "InitialApplications": "No",
    "CV": "https://drive.google.com/open?id=1ilf5ao5FOigwt7BK-sUGmFUyu8llcpUG"
  },
  {
    "TimeStamp": "8/30/2022 11:32:18",
    "Name": "tony",
    "Email": "tooneynta92@gmail.com",
    "InitialApplications": "No",
    "CV": "https://drive.google.com/open?id=1ZN7GBcBRiLmp2paHbrp4VqVO6PXY1wq9RrGSqc-4hho"
  },
  {
    "TimeStamp": "8/30/2022 12:13:36",
    "Name": "Leo",
    "Email": "Justclick@yahoo.com",
    "InitialApplications": "Yes",
    "CV": "https://drive.google.com/open?id=1PP-IoJ0lcU8hA026HgQiw4w2X71UG-3x"
  }
]